tensorflow_caney/__init__.py
tensorflow_caney/config/__init__.py
tensorflow_caney/config/cnn_config.py
tensorflow_caney/inference/__init__.py
tensorflow_caney/inference/inference.py
tensorflow_caney/inference/mem_mosaic.py
tensorflow_caney/inference/mosaic.py
tensorflow_caney/inference/regression_inference.py
tensorflow_caney/model/__init__.py
tensorflow_caney/model/geospatial_file.py
tensorflow_caney/model/vegetation_indices.py
tensorflow_caney/model/config/__init__.py
tensorflow_caney/model/config/cnn_config.py
tensorflow_caney/model/dataloaders/__init__.py
tensorflow_caney/model/dataloaders/regression.py
tensorflow_caney/model/dataloaders/segmentation.py
tensorflow_caney/model/losses/__init__.py
tensorflow_caney/model/losses/binary_focal_loss.py
tensorflow_caney/model/losses/categorical_focal_loss.py
tensorflow_caney/model/networks/__init__.py
tensorflow_caney/model/networks/classification/__init__.py
tensorflow_caney/model/networks/classification/waveform_1d_cnn.py
tensorflow_caney/model/networks/regression/__init__.py
tensorflow_caney/model/networks/regression/regression_unet.py
tensorflow_caney/model/networks/vision/__init__.py
tensorflow_caney/model/networks/vision/segmentation_unet.py
tensorflow_caney/model/networks/vision/transformers/__init__.py
tensorflow_caney/model/networks/vision/transformers/swin_layers.py
tensorflow_caney/model/networks/vision/transformers/swin_unet.py
tensorflow_caney/model/networks/vision/transformers/transformer_layers.py
tensorflow_caney/model/networks/vision/transformers/util_layers.py
tensorflow_caney/model/networks/vision/transformers/utils.py
tensorflow_caney/model/pipelines/__init__.py
tensorflow_caney/model/pipelines/cnn_regression.py
tensorflow_caney/model/pipelines/cnn_segmentation.py
tensorflow_caney/networks/Xception.py
tensorflow_caney/networks/__init__.py
tensorflow_caney/networks/deeplabv3_plus.py
tensorflow_caney/networks/unet.py
tensorflow_caney/networks/regression/__init__.py
tensorflow_caney-0.5.1.dist-info/LICENSE.md
tensorflow_caney-0.5.1.dist-info/METADATA
tensorflow_caney-0.5.1.dist-info/WHEEL
tensorflow_caney-0.5.1.dist-info/entry_points.txt
tensorflow_caney-0.5.1.dist-info/top_level.txt
tensorflow_caney-0.5.1.dist-info/zip-safe
tensorflow_caney-0.5.1.dist-info/RECORD
