Metadata-Version: 2.1
Name: tensorflow-caney
Version: 0.5.1
Summary: Methods for tensorflow deep learning applications
Home-page: https://github.com/nasa-nccs-hpda/tensorflow-caney
Author: jordancaraballo
Author-email: jordan.a.caraballo-vega@nasa.gov
License: MIT
Project-URL: Documentation, https://github.com/nasa-nccs-hpda/tensorflow-caney
Project-URL: Source, https://github.com/nasa-nccs-hpda/tensorflow-caney
Project-URL: Issues, https://github.com/nasa-nccs-hpda/tensorflow-caney/issues
Keywords: tensorflow-caney,deep-learning,machine-learning
Classifier: Development Status :: 4 - Beta
Classifier: Intended Audience :: Developers
Classifier: Intended Audience :: Science/Research
Classifier: Topic :: Software Development :: Libraries :: Python Modules
Classifier: License :: OSI Approved :: MIT License
Classifier: Programming Language :: Python :: 3 :: Only
Requires-Python: >=3.8
License-File: LICENSE.md
Requires-Dist: omegaconf
Requires-Dist: numpy
Requires-Dist: pandas
Requires-Dist: tqdm
Requires-Dist: tensorflow
Requires-Dist: segmentation-models
Requires-Dist: xarray
Requires-Dist: rioxarray
Requires-Dist: numba
Requires-Dist: keras-unet-collection
Requires-Dist: scikit-learn
Provides-Extra: all
Requires-Dist: pdoc==8.0.1; extra == "all"
Requires-Dist: tensorflow; extra == "all"
Requires-Dist: pytest; extra == "all"
Requires-Dist: coverage[toml]; extra == "all"
Requires-Dist: black; extra == "all"
Provides-Extra: docs
Requires-Dist: pdoc==8.0.1; extra == "docs"
Requires-Dist: tensorflow; extra == "docs"
Provides-Extra: test
Requires-Dist: pytest; extra == "test"
Requires-Dist: coverage[toml]; extra == "test"
Requires-Dist: black; extra == "test"
Requires-Dist: tensorflow; extra == "test"
